chatbot_help/__init__.py
chatbot_help/version.py
chatbot_help/dingtalk/__init__.py
chatbot_help/dingtalk/dingtalkbot.py
chatbot_help/qqtalk/__init__.py
chatbot_help/wetalk/__init__.py
tests/__init__.py
tests/dingtalk_test.py
chatbot_help-1.0.0.dist-info/METADATA
chatbot_help-1.0.0.dist-info/WHEEL
chatbot_help-1.0.0.dist-info/top_level.txt
chatbot_help-1.0.0.dist-info/RECORD
