Metadata-Version: 2.1
Name: chatbot-help
Version: 1.0.0
Summary: An useful tool to help your chatbot to connect third platform, such as dingtalk, wetalk
Home-page: https://github.com/charlesXu86/Chatbot_Help
Author: Xu
Author-email: charlesxu86@163.com
License: MIT Licence
Keywords: 钉钉 机器人 dingtalk chatbot robot bot 微信机器人 qq机器人
Platform: UNKNOWN
Classifier: Development Status :: 5 - Production/Stable
Classifier: Programming Language :: Python :: 3.4
Classifier: Programming Language :: Python :: 3.5
Classifier: Programming Language :: Python :: 3.6
Classifier: Programming Language :: Python :: 3.7
Requires-Python: !=3.0.*, !=3.1.*, !=3.2.*, !=3.3.*, <4
